dncil/__init__.py
dncil/version.py
dncil/cil/__init__.py
dncil/cil/enums.py
dncil/cil/error.py
dncil/cil/exception.py
dncil/cil/instruction.py
dncil/cil/opcode.py
dncil/cil/body/__init__.py
dncil/cil/body/flags.py
dncil/cil/body/reader.py
dncil/clr/__init__.py
dncil/clr/argument.py
dncil/clr/local.py
dncil/clr/token.py
dncil-1.0.2.dist-info/LICENSE.txt
dncil-1.0.2.dist-info/METADATA
dncil-1.0.2.dist-info/WHEEL
dncil-1.0.2.dist-info/top_level.txt
dncil-1.0.2.dist-info/RECORD
