Metadata-Version: 2.1
Name: dncil
Version: 1.0.2
Summary: The FLARE team's open-source library to disassemble Common Intermediate Language (CIL) instructions.
Home-page: https://www.github.com/mandiant/dncil
Author: Mike Hunhoff
Author-email: michael.hunhoff@mandiant.com
License: UNKNOWN
Keywords: .net dotnet cil il disassembly FLARE
Platform: UNKNOWN
Classifier: Development Status :: 5 - Production/Stable
Classifier: Intended Audience :: Developers
Classifier: Intended Audience :: Information Technology
Classifier: License :: OSI Approved :: Apache Software License
Classifier: Natural Language :: English
Classifier: Programming Language :: Python :: 3
Classifier: Topic :: Security
Requires-Python: >=3.7
Provides-Extra: dev
